Metadata-Version: 2.1
Name: xar
Version: 20.12.2
Summary: The XAR packaging toolchain.
Home-page: https://github.com/facebookincubator/xar
Author: Chip Turner
Author-email: chip@fb.com
License: BSD
Platform: UNKNOWN
Classifier: Development Status :: 3 - Alpha
Classifier: Environment :: Console
Classifier: Framework :: Setuptools Plugin
Classifier: Intended Audience :: Developers
Classifier: License :: OSI Approved :: BSD License
Classifier: Programming Language :: Python
Classifier: Programming Language :: Python :: 2.7
Classifier: Programming Language :: Python :: 3.6
Requires-Dist: pip (>=10.0.1)
Requires-Dist: setuptools (>=34.1)
